torchfields/__init__.py
torchfields/fields.py
torchfields/inversion.py
torchfields/utils.py
torchfields/voting.py
torchfields-0.1.2.dist-info/AUTHORS
torchfields-0.1.2.dist-info/LICENSE
torchfields-0.1.2.dist-info/METADATA
torchfields-0.1.2.dist-info/WHEEL
torchfields-0.1.2.dist-info/pbr.json
torchfields-0.1.2.dist-info/top_level.txt
torchfields-0.1.2.dist-info/RECORD
