Metadata-Version: 2.1
Name: torchfields
Version: 0.1.2
Summary: A PyTorch add-on for working with image mappings and displacement fields, including Spatial Transformers
Home-page: https://github.com/seung-lab/torchfields
Author: Barak Nehoran, Nico Kemnitz
Author-email: bnehoran@users.noreply.github.com, nkemnitz@users.noreply.github.com
License: MIT
Platform: UNKNOWN
Classifier: Intended Audience :: Developers
Classifier: Development Status :: 4 - Beta
Classifier: Programming Language :: Python :: 3
Classifier: Programming Language :: Python :: 3.7
Classifier: Programming Language :: Python :: 3.8
Classifier: Programming Language :: Python :: 3.9
Classifier: Programming Language :: Python :: 3.10
Classifier: Topic :: Scientific/Engineering
Classifier: License :: OSI Approved :: MIT License
License-File: LICENSE
License-File: AUTHORS
Requires-Dist: torch (>=1.7.0)
Requires-Dist: setuptools (>=34.0.0)
